file_uploader/__init__.py
file_uploader/uploader.py
s3_file_uploader-0.1.0.dist-info/licenses/LICENSE
s3_file_uploader-0.1.0.dist-info/METADATA
s3_file_uploader-0.1.0.dist-info/WHEEL
s3_file_uploader-0.1.0.dist-info/top_level.txt
s3_file_uploader-0.1.0.dist-info/RECORD
